pysomneoctrl/ConstSomneo.py
pysomneoctrl/SomneoAlarmManager.py
pysomneoctrl/SomneoAudioManager.py
pysomneoctrl/SomneoDevice.py
pysomneoctrl/SomneoHttp.py
pysomneoctrl/SomneoWindDown.py
pysomneoctrl/__init__.py
pysomneoctrl/paths.py
pysomneoctrl-1.0.4.dist-info/LICENSE
pysomneoctrl-1.0.4.dist-info/METADATA
pysomneoctrl-1.0.4.dist-info/WHEEL
pysomneoctrl-1.0.4.dist-info/top_level.txt
pysomneoctrl-1.0.4.dist-info/RECORD
