Metadata-Version: 2.1
Name: pysomneoctrl
Version: 1.0.4
Summary: Python package for Philips Somneo
Home-page: https://github.com/pijiulaoshi/pysomneoctrl
Author: PijiuLaoshi
Author-email: pijiulaoshi@gmail.com
License: UNKNOWN
Project-URL: Bug Tracker, https://github.com/pijiulaoshi/pysomneoctrl/issues
Platform: UNKNOWN
Classifier: Programming Language :: Python :: 3
Classifier: License :: OSI Approved :: MIT License
Classifier: Operating System :: OS Independent
Requires-Python: >=3.6
License-File: LICENSE
